FruceAPI/__init__.py
FruceAPI/__pycache__/__init__.cpython-311.pyc
FruceAPI/exceptions/__init__.py
FruceAPI/exceptions/__pycache__/__init__.cpython-311.pyc
FruceAPI/objects/__init__.py
FruceAPI/objects/__pycache__/__init__.cpython-311.pyc
FruceAPI/objects/__pycache__/__init___.cpython-311.pyc
FruceAPI/utils/__init__.py
FruceAPI/utils/__pycache__/__init__.cpython-311.pyc
FruceAPI-1.2.3.dist-info/METADATA
FruceAPI-1.2.3.dist-info/WHEEL
FruceAPI-1.2.3.dist-info/top_level.txt
FruceAPI-1.2.3.dist-info/RECORD
