Metadata-Version: 2.1
Name: FruceAPI
Version: 1.2.3
Summary: FruceAPI is a easy tool for working with FruitSpace hosting
Home-page: https://github.com/catvibriss/FruceAPI
Author: kottvpalto
Author-email: kotvpaltoof@ya.ru
Classifier: Programming Language :: Python :: 3
Classifier: License :: OSI Approved :: MIT License
Classifier: Operating System :: OS Independent
Requires-Python: >=3.6
Requires-Dist: aiohttp
